LICENSE
MANIFEST.in
README.md
jingbao_fuwuqi.py
setup.py
jingbao_fuwuqi.egg-info/PKG-INFO
jingbao_fuwuqi.egg-info/SOURCES.txt
jingbao_fuwuqi.egg-info/dependency_links.txt
jingbao_fuwuqi.egg-info/entry_points.txt
jingbao_fuwuqi.egg-info/requires.txt
jingbao_fuwuqi.egg-info/top_level.txt