Metadata-Version: 1.0
Name: jingbao-fuwuqi
Version: 2017.1.16.1621
Summary: alert when server available
Home-page: https://github.com/wdbm/jingbao-fuwuqi
Author: Will Breaden Madden
Author-email: wbm@protonmail.ch
License: GPLv3
Platform: UNKNOWN
